./.gitignore
./LICENSE.md
./PKG-INFO
./README.md
./createKmer.py
./main.py
./pyproject.toml
./src/spyce/__init__.py
./src/spyce/compare.py
./src/spyce/constants.py
./src/spyce/dataType.py
./src/spyce/kmerMatrix.py
./src/spyce/normalize.py
./src/spyce/plotting.py
./src/spyce/tf.py
./src/spyce/utils.py
spyce/__init__.py
spyce/compare.py
spyce/constants.py
spyce/dataType.py
spyce/kmerMatrix.py
spyce/normalize.py
spyce/plotting.py
spyce/tf.py
spyce/utils.py
spyceatac-0.1.2.dist-info/METADATA
spyceatac-0.1.2.dist-info/WHEEL
spyceatac-0.1.2.dist-info/entry_points.txt
spyceatac-0.1.2.dist-info/licenses/LICENSE.md
spyceatac-0.1.2.dist-info/RECORD
