Metadata-Version: 2.4
Name: spyceATAC
Version: 0.1.2
Summary: sPYce is a Python package for the cross-species integration of single-nucleus ATAC-seq data (snATAC-seq)
Project-URL: Documentation, https://cofugeno.pages.pasteur.fr/spyce/
Project-URL: Repository, https://gitlab.pasteur.fr/cofugeno/spyce
Project-URL: Issues, https://gitlab.pasteur.fr/cofugeno/spyce/-/issues
Author-email: Leo Zeitler <leo.zeitler@pasteur.fr>
License-Expression: CC-BY-NC-SA-4.0
License-File: LICENSE.md
Keywords: atac,cross-species,data integration,evolution,single cell,single nucleus,snatac-seq
Classifier: Operating System :: OS Independent
Classifier: Programming Language :: Python :: 3
Requires-Python: >=3.6
Requires-Dist: anndata==0.10.8
Requires-Dist: dill~=0.3.8
Requires-Dist: gimmemotifs~=0.18.0
Requires-Dist: harmonypy~=0.0.10
Requires-Dist: igraph~=0.11.4
Requires-Dist: jax==0.4.23
Requires-Dist: jaxlib==0.4.23
Requires-Dist: leidenalg~=0.10.1
Requires-Dist: logomaker~=0.8
Requires-Dist: matplotlib~=3.8.4
Requires-Dist: networkx~=3.2.1
Requires-Dist: numba~=0.59.1
Requires-Dist: numpy~=1.23.5
Requires-Dist: pandas<2.0.0
Requires-Dist: polars~=1.19.0
Requires-Dist: pysam~=0.22.1
Requires-Dist: scikit-learn~=1.3.2
Requires-Dist: scipy==1.12.0
Requires-Dist: seaborn~=0.13.2
Requires-Dist: tqdm~=4.66.4
Requires-Dist: umap-learn~=0.5.6
